{
    "ABACUS": "0x1F9EE",
    "ADHESIVE_BANDAGE": "0x1FA79",
    "ADMISSION_TICKETS": "0x1F39F",
    "ADULT": "0x1F9D1",
    "AERIAL_TRAMWAY": "0x1F6A1",
    "AIRPLANE": "0x2708",
    "AIRPLANE_ARRIVING": "0x1F6EC",
    "AIRPLANE_DEPARTURE": "0x1F6EB",
    "ALARM_CLOCK": "0x23F0",
    "ALEMBIC": "0x2697",
    "ALIEN_MONSTER": "0x1F47E",
    "AMBULANCE": "0x1F691",
    "AMERICAN_FOOTBALL": "0x1F3C8",
    "AMPHORA": "0x1F3FA",
    "ANCHOR": "0x2693",
    "ANGER_SYMBOL": "0x1F4A2",
    "ANGRY_FACE": "0x1F620",
    "ANGUISHED_FACE": "0x1F627",
    "ANT": "0x1F41C",
    "ANTENNA_WITH_BARS": "0x1F4F6",
    "ANTICLOCKWISE_DOWNWARDS_AND_UPWARDS_OPEN_CIRCLE_ARROWS": "0x1F504",
    "AQUARIUS": "0x2652",
    "ARIES": "0x2648",
    "ARROW_POINTING_RIGHTWARDS_THEN_CURVING_DOWNWARDS": "0x2935",
    "ARROW_POINTING_RIGHTWARDS_THEN_CURVING_UPWARDS": "0x2934",
    "ARTICULATED_LORRY": "0x1F69B",
    "ARTIST_PALETTE": "0x1F3A8",
    "ASTERISK": "0x002A",
    "ASTONISHED_FACE": "0x1F632",
    "ATHLETIC_SHOE": "0x1F45F",
    "ATOM_SYMBOL": "0x269B",
    "AUBERGINE": "0x1F346",
    "AUTOMATED_TELLER_MACHINE": "0x1F3E7",
    "AUTOMOBILE": "0x1F697",
    "AUTO_RICKSHAW": "0x1F6FA",
    "AVOCADO": "0x1F951",
    "AXE": "0x1FA93",
    "BABY": "0x1F476",
    "BABY_ANGEL": "0x1F47C",
    "BABY_BOTTLE": "0x1F37C",
    "BABY_CHICK": "0x1F424",
    "BABY_SYMBOL": "0x1F6BC",
    "BACK_WITH_LEFTWARDS_ARROW_ABOVE": "0x1F519",
    "BACON": "0x1F953",
    "BACTRIAN_CAMEL": "0x1F42B",
    "BADGER": "0x1F9A1",
    "BADMINTON_RACQUET_AND_SHUTTLECOCK": "0x1F3F8",
    "BAGEL": "0x1F96F",
    "BAGGAGE_CLAIM": "0x1F6C4",
    "BAGUETTE_BREAD": "0x1F956",
    "BALLET_SHOES": "0x1FA70",
    "BALLOON": "0x1F388",
    "BALLOT_BOX_WITH_BALLOT": "0x1F5F3",
    "BALLOT_BOX_WITH_CHECK": "0x2611",
    "BALL_OF_YARN": "0x1F9F6",
    "BANANA": "0x1F34C",
    "BANJO": "0x1FA95",
    "BANK": "0x1F3E6",
    "BANKNOTE_WITH_DOLLAR_SIGN": "0x1F4B5",
    "BANKNOTE_WITH_EURO_SIGN": "0x1F4B6",
    "BANKNOTE_WITH_POUND_SIGN": "0x1F4B7",
    "BANKNOTE_WITH_YEN_SIGN": "0x1F4B4",
    "BARBER_POLE": "0x1F488",
    "BAR_CHART": "0x1F4CA",
    "BAR_OF_SOAP": "0x1F9FC",
    "BASEBALL": "0x26BE",
    "BASKET": "0x1F9FA",
    "BASKETBALL_AND_HOOP": "0x1F3C0",
    "BAT": "0x1F987",
    "BATH": "0x1F6C0",
    "BATHTUB": "0x1F6C1",
    "BATTERY": "0x1F50B",
    "BEACH_WITH_UMBRELLA": "0x1F3D6",
    "BEARDED_PERSON": "0x1F9D4",
    "BEAR_FACE": "0x1F43B",
    "BEATING_HEART": "0x1F493",
    "BED": "0x1F6CF",
    "BEER_MUG": "0x1F37A",
    "BELL": "0x1F514",
    "BELLHOP_BELL": "0x1F6CE",
    "BELL_WITH_CANCELLATION_STROKE": "0x1F515",
    "BENTO_BOX": "0x1F371",
    "BEVERAGE_BOX": "0x1F9C3",
    "BICYCLE": "0x1F6B2",
    "BICYCLIST": "0x1F6B4",
    "BIKINI": "0x1F459",
    "BILLED_CAP": "0x1F9E2",
    "BILLIARDS": "0x1F3B1",
    "BIOHAZARD_SIGN": "0x2623",
    "BIRD": "0x1F426",
    "BIRTHDAY_CAKE": "0x1F382",
    "BLACK_CIRCLE_FOR_RECORD": "0x23FA",
    "BLACK_CLUB_SUIT": "0x2663",
    "BLACK_DIAMOND_SUIT": "0x2666",
    "BLACK_DOWN_POINTING_DOUBLE_TRIANGLE": "0x23EC",
    "BLACK_HEART": "0x1F5A4",
    "BLACK_HEART_SUIT": "0x2665",
    "BLACK_LARGE_SQUARE": "0x2B1B",
    "BLACK_LEFT_POINTING_DOUBLE_TRIANGLE": "0x23EA",
    "BLACK_LEFT_POINTING_DOUBLE_TRIANGLE_WITH_VERTICAL_BAR": "0x23EE",
    "BLACK_LEFT_POINTING_TRIANGLE": "0x25C0",
    "BLACK_MEDIUM_SMALL_SQUARE": "0x25FE",
    "BLACK_MEDIUM_SQUARE": "0x25FC",
    "BLACK_NIB": "0x2712",
    "BLACK_QUESTION_MARK_ORNAMENT": "0x2753",
    "BLACK_RIGHT_POINTING_DOUBLE_TRIANGLE": "0x23E9",
    "BLACK_RIGHT_POINTING_DOUBLE_TRIANGLE_WITH_VERTICAL_BAR": "0x23ED",
    "BLACK_RIGHT_POINTING_TRIANGLE": "0x25B6",
    "BLACK_RIGHT_POINTING_TRIANGLE_WITH_DOUBLE_VERTICAL_BAR": "0x23EF",
    "BLACK_RIGHTWARDS_ARROW": "0x27A1",
    "BLACK_SCISSORS": "0x2702",
    "BLACK_SMALL_SQUARE": "0x25AA",
    "BLACK_SPADE_SUIT": "0x2660",
    "BLACK_SQUARE_BUTTON": "0x1F532",
    "BLACK_SQUARE_FOR_STOP": "0x23F9",
    "BLACK_SUN_WITH_RAYS": "0x2600",
    "BLACK_TELEPHONE": "0x260E",
    "BLACK_UNIVERSAL_RECYCLING_SYMBOL": "0x267B",
    "BLACK_UP_POINTING_DOUBLE_TRIANGLE": "0x23EB",
    "BLOSSOM": "0x1F33C",
    "BLOWFISH": "0x1F421",
    "BLUE_BOOK": "0x1F4D8",
    "BLUE_HEART": "0x1F499",
    "BOAR": "0x1F417",
    "BOMB": "0x1F4A3",
    "BONE": "0x1F9B4",
    "BOOKMARK": "0x1F516",
    "BOOKMARK_TABS": "0x1F4D1",
    "BOOKS": "0x1F4DA",
    "BOTTLE_WITH_POPPING_CORK": "0x1F37E",
    "BOUQUET": "0x1F490",
    "BOWLING": "0x1F3B3",
    "BOWL_WITH_SPOON": "0x1F963",
    "BOW_AND_ARROW": "0x1F3F9",
    "BOXING_GLOVE": "0x1F94A",
    "BOY": "0x1F466",
    "BRAIN": "0x1F9E0",
    "BREAD": "0x1F35E",
    "BRICK": "0x1F9F1",
    "BRIDE_WITH_VEIL": "0x1F470",
    "BRIDGE_AT_NIGHT": "0x1F309",
    "BRIEFCASE": "0x1F4BC",
    "BRIEFS": "0x1FA72",
    "BROCCOLI": "0x1F966",
    "BROKEN_HEART": "0x1F494",
    "BROOM": "0x1F9F9",
    "BROWN_HEART": "0x1F90E",
    "BUG": "0x1F41B",
    "BUILDING_CONSTRUCTION": "0x1F3D7",
    "BURRITO": "0x1F32F",
    "BUS": "0x1F68C",
    "BUSTS_IN_SILHOUETTE": "0x1F465",
    "BUST_IN_SILHOUETTE": "0x1F464",
    "BUS_STOP": "0x1F68F",
    "BUTTER": "0x1F9C8",
    "BUTTERFLY": "0x1F98B",
    "CACTUS": "0x1F335",
    "CALENDAR": "0x1F4C5",
    "CALL_ME_HAND": "0x1F919",
    "CAMERA": "0x1F4F7",
    "CAMERA_WITH_FLASH": "0x1F4F8",
    "CAMPING": "0x1F3D5",
    "CANCER": "0x264B",
    "CANDLE": "0x1F56F",
    "CANDY": "0x1F36C",
    "CANNED_FOOD": "0x1F96B",
    "CANOE": "0x1F6F6",
    "CAPRICORN": "0x2651",
    "CARD_FILE_BOX": "0x1F5C3",
    "CARD_INDEX": "0x1F4C7",
    "CARD_INDEX_DIVIDERS": "0x1F5C2",
    "CAROUSEL_HORSE": "0x1F3A0",
    "CARP_STREAMER": "0x1F38F",
    "CARROT": "0x1F955",
    "CAT": "0x1F408",
    "CAT_FACE": "0x1F431",
    "CAT_FACE_WITH_TEARS_OF_JOY": "0x1F639",
    "CAT_FACE_WITH_WRY_SMILE": "0x1F63C",
    "CHAINS": "0x26D3",
    "CHAIR": "0x1FA91",
    "CHART_WITH_DOWNWARDS_TREND": "0x1F4C9",
    "CHART_WITH_UPWARDS_TREND": "0x1F4C8",
    "CHART_WITH_UPWARDS_TREND_AND_YEN_SIGN": "0x1F4B9",
    "CHEERING_MEGAPHONE": "0x1F4E3",
    "CHEESE_WEDGE": "0x1F9C0",
    "CHEQUERED_FLAG": "0x1F3C1",
    "CHERRIES": "0x1F352",
    "CHERRY_BLOSSOM": "0x1F338",
    "CHESS_PAWN": "0x265F",
    "CHESTNUT": "0x1F330",
    "CHICKEN": "0x1F414",
    "CHILD": "0x1F9D2",
    "CHILDREN_CROSSING": "0x1F6B8",
    "CHIPMUNK": "0x1F43F",
    "CHOCOLATE_BAR": "0x1F36B",
    "CHOPSTICKS": "0x1F962",
    "CHRISTMAS_TREE": "0x1F384",
    "CHURCH": "0x26EA",
    "CINEMA": "0x1F3A6",
    "CIRCLED_IDEOGRAPH_ACCEPT": "0x1F251",
    "CIRCLED_IDEOGRAPH_ADVANTAGE": "0x1F250",
    "CIRCLED_IDEOGRAPH_CONGRATULATION": "0x3297",
    "CIRCLED_IDEOGRAPH_SECRET": "0x3299",
    "CIRCLED_LATIN_CAPITAL_LETTER_M": "0x24C2",
    "CIRCUS_TENT": "0x1F3AA",
    "CITYSCAPE": "0x1F3D9",
    "CITYSCAPE_AT_DUSK": "0x1F306",
    "CLAPPER_BOARD": "0x1F3AC",
    "CLAPPING_HANDS_SIGN": "0x1F44F",
    "CLASSICAL_BUILDING": "0x1F3DB",
    "CLINKING_BEER_MUGS": "0x1F37B",
    "CLINKING_GLASSES": "0x1F942",
    "CLIPBOARD": "0x1F4CB",
    "CLOCKWISE_DOWNWARDS_AND_UPWARDS_OPEN_CIRCLE_ARROWS": "0x1F503",
    "CLOCKWISE_RIGHTWARDS_AND_LEFTWARDS_OPEN_CIRCLE_ARROWS": "0x1F501",
    "CLOCKWISE_RIGHTWARDS_AND_LEFTWARDS_OPEN_CIRCLE_ARROWS_WITH_CIRCLED_ONE_OVERLAY": "0x1F502",
    "CLOCK_FACE_EIGHT_THIRTY": "0x1F563",
    "CLOCK_FACE_EIGHT_OCLOCK": "0x1F557",
    "CLOCK_FACE_ELEVEN_THIRTY": "0x1F566",
    "CLOCK_FACE_ELEVEN_OCLOCK": "0x1F55A",
    "CLOCK_FACE_FIVE_THIRTY": "0x1F560",
    "CLOCK_FACE_FIVE_OCLOCK": "0x1F554",
    "CLOCK_FACE_FOUR_THIRTY": "0x1F55F",
    "CLOCK_FACE_FOUR_OCLOCK": "0x1F553",
    "CLOCK_FACE_NINE_THIRTY": "0x1F564",
    "CLOCK_FACE_NINE_OCLOCK": "0x1F558",
    "CLOCK_FACE_ONE_THIRTY": "0x1F55C",
    "CLOCK_FACE_ONE_OCLOCK": "0x1F550",
    "CLOCK_FACE_SEVEN_THIRTY": "0x1F562",
    "CLOCK_FACE_SEVEN_OCLOCK": "0x1F556",
    "CLOCK_FACE_SIX_THIRTY": "0x1F561",
    "CLOCK_FACE_SIX_OCLOCK": "0x1F555",
    "CLOCK_FACE_TEN_THIRTY": "0x1F565",
    "CLOCK_FACE_TEN_OCLOCK": "0x1F559",
    "CLOCK_FACE_THREE_THIRTY": "0x1F55E",
    "CLOCK_FACE_THREE_OCLOCK": "0x1F552",
    "CLOCK_FACE_TWELVE_THIRTY": "0x1F567",
    "CLOCK_FACE_TWELVE_OCLOCK": "0x1F55B",
    "CLOCK_FACE_TWO_THIRTY": "0x1F55D",
    "CLOCK_FACE_TWO_OCLOCK": "0x1F551",
    "CLOSED_BOOK": "0x1F4D5",
    "CLOSED_LOCK_WITH_KEY": "0x1F510",
    "CLOSED_MAILBOX_WITH_LOWERED_FLAG": "0x1F4EA",
    "CLOSED_MAILBOX_WITH_RAISED_FLAG": "0x1F4EB",
    "CLOSED_UMBRELLA": "0x1F302",
    "CLOUD": "0x2601",
    "CLOUD_WITH_LIGHTNING": "0x1F329",
    "CLOUD_WITH_RAIN": "0x1F327",
    "CLOUD_WITH_SNOW": "0x1F328",
    "CLOUD_WITH_TORNADO": "0x1F32A",
    "CLOWN_FACE": "0x1F921",
    "COAT": "0x1F9E5",
    "COCKTAIL_GLASS": "0x1F378",
    "COCONUT": "0x1F965",
    "COFFIN": "0x26B0",
    "COLLISION_SYMBOL": "0x1F4A5",
    "COMET": "0x2604",
    "COMPASS": "0x1F9ED",
    "COMPRESSION": "0x1F5DC",
    "CONFETTI_BALL": "0x1F38A",
    "CONFOUNDED_FACE": "0x1F616",
    "CONFUSED_FACE": "0x1F615",
    "CONSTRUCTION_SIGN": "0x1F6A7",
    "CONSTRUCTION_WORKER": "0x1F477",
    "CONTROL_KNOBS": "0x1F39B",
    "CONVENIENCE_STORE": "0x1F3EA",
    "COOKED_RICE": "0x1F35A",
    "COOKIE": "0x1F36A",
    "COOKING": "0x1F373",
    "COPYRIGHT_SIGN": "0x00A9",
    "COUCH_AND_LAMP": "0x1F6CB",
    "COUPLE_WITH_HEART": "0x1F491",
    "COW": "0x1F404",
    "COW_FACE": "0x1F42E",
    "CRAB": "0x1F980",
    "CREDIT_CARD": "0x1F4B3",
    "CRESCENT_MOON": "0x1F319",
    "CRICKET": "0x1F997",
    "CRICKET_BAT_AND_BALL": "0x1F3CF",
    "CROCODILE": "0x1F40A",
    "CROISSANT": "0x1F950",
    "CROSSED_FLAGS": "0x1F38C",
    "CROSSED_SWORDS": "0x2694",
    "CROSS_MARK": "0x274C",
    "CROWN": "0x1F451",
    "CRYING_CAT_FACE": "0x1F63F",
    "CRYING_FACE": "0x1F622",
    "CRYSTAL_BALL": "0x1F52E",
    "CUCUMBER": "0x1F952",
    "CUPCAKE": "0x1F9C1",
    "CUP_WITH_STRAW": "0x1F964",
    "CURLY_LOOP": "0x27B0",
    "CURRENCY_EXCHANGE": "0x1F4B1",
    "CURRY_AND_RICE": "0x1F35B",
    "CUSTARD": "0x1F36E",
    "CUSTOMS": "0x1F6C3",
    "CUT_OF_MEAT": "0x1F969",
    "CYCLONE": "0x1F300",
    "DAGGER_KNIFE": "0x1F5E1",
    "DANCER": "0x1F483",
    "DANGO": "0x1F361",
    "DARK_SUNGLASSES": "0x1F576",
    "DASH_SYMBOL": "0x1F4A8",
    "DEAF_PERSON": "0x1F9CF",
    "DECIDUOUS_TREE": "0x1F333",
    "DEER": "0x1F98C",
    "DELIVERY_TRUCK": "0x1F69A",
    "DEPARTMENT_STORE": "0x1F3EC",
    "DERELICT_HOUSE_BUILDING": "0x1F3DA",
    "DESERT": "0x1F3DC",
    "DESERT_ISLAND": "0x1F3DD",
    "DESKTOP_COMPUTER": "0x1F5A5",
    "DIAMOND_SHAPE_WITH_A_DOT_INSIDE": "0x1F4A0",
    "DIGIT_EIGHT": "0x0038",
    "DIGIT_FIVE": "0x0035",
    "DIGIT_FOUR": "0x0034",
    "DIGIT_NINE": "0x0039",
    "DIGIT_ONE": "0x0031",
    "DIGIT_SEVEN": "0x0037",
    "DIGIT_SIX": "0x0036",
    "DIGIT_THREE": "0x0033",
    "DIGIT_TWO": "0x0032",
    "DIGIT_ZERO": "0x0030",
    "DIRECT_HIT": "0x1F3AF",
    "DISAPPOINTED_BUT_RELIEVED_FACE": "0x1F625",
    "DISAPPOINTED_FACE": "0x1F61E",
    "DIVING_MASK": "0x1F93F",
    "DIYA_LAMP": "0x1FA94",
    "DIZZY_FACE": "0x1F635",
    "DIZZY_SYMBOL": "0x1F4AB",
    "DNA_DOUBLE_HELIX": "0x1F9EC",
    "DOG": "0x1F415",
    "DOG_FACE": "0x1F436",
    "DOLPHIN": "0x1F42C",
    "DOOR": "0x1F6AA",
    "DOUBLE_CURLY_LOOP": "0x27BF",
    "DOUBLE_EXCLAMATION_MARK": "0x203C",
    "DOUBLE_VERTICAL_BAR": "0x23F8",
    "DOUGHNUT": "0x1F369",
    "DOVE_OF_PEACE": "0x1F54A",
    "DOWN_POINTING_RED_TRIANGLE": "0x1F53B",
    "DOWN_POINTING_SMALL_RED_TRIANGLE": "0x1F53D",
    "DOWNWARDS_BLACK_ARROW": "0x2B07",
    "DO_NOT_LITTER_SYMBOL": "0x1F6AF",
    "DRAGON": "0x1F409",
    "DRAGON_FACE": "0x1F432",
    "DRESS": "0x1F457",
    "DROMEDARY_CAMEL": "0x1F42A",
    "DROOLING_FACE": "0x1F924",
    "DROPLET": "0x1F4A7",
    "DROP_OF_BLOOD": "0x1FA78",
    "DRUM_WITH_DRUMSTICKS": "0x1F941",
    "DUCK": "0x1F986",
    "DUMPLING": "0x1F95F",
    "DVD": "0x1F4C0",
    "E_MAIL_SYMBOL": "0x1F4E7",
    "EAGLE": "0x1F985",
    "EAR": "0x1F442",
    "EARTH_GLOBE_AMERICAS": "0x1F30E",
    "EARTH_GLOBE_ASIA_AUSTRALIA": "0x1F30F",
    "EARTH_GLOBE_EUROPE_AFRICA": "0x1F30D",
    "EAR_OF_MAIZE": "0x1F33D",
    "EAR_OF_RICE": "0x1F33E",
    "EAR_WITH_HEARING_AID": "0x1F9BB",
    "EGG": "0x1F95A",
    "EIGHT_POINTED_BLACK_STAR": "0x2734",
    "EIGHT_SPOKED_ASTERISK": "0x2733",
    "EJECT_SYMBOL": "0x23CF",
    "ELECTRIC_LIGHT_BULB": "0x1F4A1",
    "ELECTRIC_PLUG": "0x1F50C",
    "ELECTRIC_TORCH": "0x1F526",
    "ELEPHANT": "0x1F418",
    "ELF": "0x1F9DD",
    "EMOJI_COMPONENT_BALD": "0x1F9B2",
    "EMOJI_COMPONENT_CURLY_HAIR": "0x1F9B1",
    "EMOJI_COMPONENT_RED_HAIR": "0x1F9B0",
    "EMOJI_COMPONENT_WHITE_HAIR": "0x1F9B3",
    "EMOJI_MODIFIER_FITZPATRICK_TYPE_1_2": "0x1F3FB",
    "EMOJI_MODIFIER_FITZPATRICK_TYPE_3": "0x1F3FC",
    "EMOJI_MODIFIER_FITZPATRICK_TYPE_4": "0x1F3FD",
    "EMOJI_MODIFIER_FITZPATRICK_TYPE_5": "0x1F3FE",
    "EMOJI_MODIFIER_FITZPATRICK_TYPE_6": "0x1F3FF",
    "END_WITH_LEFTWARDS_ARROW_ABOVE": "0x1F51A",
    "ENVELOPE": "0x2709",
    "ENVELOPE_WITH_DOWNWARDS_ARROW_ABOVE": "0x1F4E9",
    "EUROPEAN_CASTLE": "0x1F3F0",
    "EUROPEAN_POST_OFFICE": "0x1F3E4",
    "EVERGREEN_TREE": "0x1F332",
    "EXCLAMATION_QUESTION_MARK": "0x2049",
    "EXPRESSIONLESS_FACE": "0x1F611",
    "EXTRATERRESTRIAL_ALIEN": "0x1F47D",
    "EYE": "0x1F441",
    "EYEGLASSES": "0x1F453",
    "EYES": "0x1F440",
    "FACE_MASSAGE": "0x1F486",
    "FACE_PALM": "0x1F926",
    "FACE_SAVOURING_DELICIOUS_FOOD": "0x1F60B",
    "FACE_SCREAMING_IN_FEAR": "0x1F631",
    "FACE_THROWING_A_KISS": "0x1F618",
    "FACE_WITHOUT_MOUTH": "0x1F636",
    "FACE_WITH_COLD_SWEAT": "0x1F613",
    "FACE_WITH_COWBOY_HAT": "0x1F920",
    "FACE_WITH_HEAD_BANDAGE": "0x1F915",
    "FACE_WITH_LOOK_OF_TRIUMPH": "0x1F624",
    "FACE_WITH_MEDICAL_MASK": "0x1F637",
    "FACE_WITH_MONOCLE": "0x1F9D0",
    "FACE_WITH_NO_GOOD_GESTURE": "0x1F645",
    "FACE_WITH_OK_GESTURE": "0x1F646",
    "FACE_WITH_OPEN_MOUTH": "0x1F62E",
    "FACE_WITH_OPEN_MOUTH_AND_COLD_SWEAT": "0x1F630",
    "FACE_WITH_PARTY_HORN_AND_PARTY_HAT": "0x1F973",
    "FACE_WITH_PLEADING_EYES": "0x1F97A",
    "FACE_WITH_ROLLING_EYES": "0x1F644",
    "FACE_WITH_STUCK_OUT_TONGUE": "0x1F61B",
    "FACE_WITH_STUCK_OUT_TONGUE_AND_TIGHTLY_CLOSED_EYES": "0x1F61D",
    "FACE_WITH_STUCK_OUT_TONGUE_AND_WINKING_EYE": "0x1F61C",
    "FACE_WITH_TEARS_OF_JOY": "0x1F602",
    "FACE_WITH_THERMOMETER": "0x1F912",
    "FACE_WITH_UNEVEN_EYES_AND_WAVY_MOUTH": "0x1F974",
    "FACTORY": "0x1F3ED",
    "FAIRY": "0x1F9DA",
    "FALAFEL": "0x1F9C6",
    "FALLEN_LEAF": "0x1F342",
    "FAMILY": "0x1F46A",
    "FATHER_CHRISTMAS": "0x1F385",
    "FAX_MACHINE": "0x1F4E0",
    "FEARFUL_FACE": "0x1F628",
    "FEMALE_SIGN": "0x2640",
    "FENCER": "0x1F93A",
    "FERRIS_WHEEL": "0x1F3A1",
    "FERRY": "0x26F4",
    "FIELD_HOCKEY_STICK_AND_BALL": "0x1F3D1",
    "FILE_CABINET": "0x1F5C4",
    "FILE_FOLDER": "0x1F4C1",
    "FILM_FRAMES": "0x1F39E",
    "FILM_PROJECTOR": "0x1F4FD",
    "FIRE": "0x1F525",
    "FIRECRACKER": "0x1F9E8",
    "FIREWORKS": "0x1F386",
    "FIREWORK_SPARKLER": "0x1F387",
    "FIRE_ENGINE": "0x1F692",
    "FIRE_EXTINGUISHER": "0x1F9EF",
    "FIRST_PLACE_MEDAL": "0x1F947",
    "FIRST_QUARTER_MOON_SYMBOL": "0x1F313",
    "FIRST_QUARTER_MOON_WITH_FACE": "0x1F31B",
    "FISH": "0x1F41F",
    "FISHING_POLE_AND_FISH": "0x1F3A3",
    "FISH_CAKE_WITH_SWIRL_DESIGN": "0x1F365",
    "FISTED_HAND_SIGN": "0x1F44A",
    "FLAG_IN_HOLE": "0x26F3",
    "FLAMINGO": "0x1F9A9",
    "FLAT_SHOE": "0x1F97F",
    "FLEUR_DE_LIS": "0x269C",
    "FLEXED_BICEPS": "0x1F4AA",
    "FLOPPY_DISK": "0x1F4BE",
    "FLOWER_PLAYING_CARDS": "0x1F3B4",
    "FLUSHED_FACE": "0x1F633",
    "FLYING_SAUCER": "0x1F6F8",
    "FOG": "0x1F32B",
    "FOGGY": "0x1F301",
    "FOOT": "0x1F9B6",
    "FOOTPRINTS": "0x1F463",
    "FORK_AND_KNIFE": "0x1F374",
    "FORK_AND_KNIFE_WITH_PLATE": "0x1F37D",
    "FORTUNE_COOKIE": "0x1F960",
    "FOUNTAIN": "0x26F2",
    "FOUR_LEAF_CLOVER": "0x1F340",
    "FOX_FACE": "0x1F98A",
    "FRAME_WITH_PICTURE": "0x1F5BC",
    "FREEZING_FACE": "0x1F976",
    "FRENCH_FRIES": "0x1F35F",
    "FRIED_SHRIMP": "0x1F364",
    "FROG_FACE": "0x1F438",
    "FRONT_FACING_BABY_CHICK": "0x1F425",
    "FROWNING_FACE_WITH_OPEN_MOUTH": "0x1F626",
    "FUEL_PUMP": "0x26FD",
    "FULL_MOON_SYMBOL": "0x1F315",
    "FULL_MOON_WITH_FACE": "0x1F31D",
    "FUNERAL_URN": "0x26B1",
    "GAME_DIE": "0x1F3B2",
    "GARLIC": "0x1F9C4",
    "GEAR": "0x2699",
    "GEMINI": "0x264A",
    "GEM_STONE": "0x1F48E",
    "GENIEA": "0x1F9DE",
    "GHOST": "0x1F47B",
    "GIRAFFE_FACE": "0x1F992",
    "GIRL": "0x1F467",
    "GLASS_OF_MILK": "0x1F95B",
    "GLOBE_WITH_MERIDIANS": "0x1F310",
    "GLOVES": "0x1F9E4",
    "GLOWING_STAR": "0x1F31F",
    "GOAL_NET": "0x1F945",
    "GOAT": "0x1F410",
    "GOGGLESS": "0x1F97D",
    "GOLFER": "0x1F3CC",
    "GORILLA": "0x1F98D",
    "GRADUATION_CAP": "0x1F393",
    "GRAPES": "0x1F347",
    "GREEN_APPLE": "0x1F34F",
    "GREEN_BOOK": "0x1F4D7",
    "GREEN_HEART": "0x1F49A",
    "GREEN_SALAD": "0x1F957",
    "GRIMACING_FACE": "0x1F62C",
    "GRINNING_CAT_FACE_WITH_SMILING_EYES": "0x1F638",
    "GRINNING_FACE": "0x1F600",
    "GRINNING_FACE_WITH_SMILING_EYES": "0x1F601",
    "GROWING_HEART": "0x1F497",
    "GUARDSMAN": "0x1F482",
    "GUIDE_DOG": "0x1F9AE",
    "GUITAR": "0x1F3B8",
    "HAIRCUT": "0x1F487",
    "HAMBURGER": "0x1F354",
    "HAMMER": "0x1F528",
    "HAMMER_AND_PICK": "0x2692",
    "HAMMER_AND_WRENCH": "0x1F6E0",
    "HAMSTER_FACE": "0x1F439",
    "HANDBAG": "0x1F45C",
    "HANDBALL": "0x1F93E",
    "HANDSHAKE": "0x1F91D",
    "HAND_WITH_INDEX_AND_MIDDLE_FINGERS_CROSSED": "0x1F91E",
    "HAPPY_PERSON_RAISING_ONE_HAND": "0x1F64B",
    "HATCHING_CHICK": "0x1F423",
    "HEADPHONE": "0x1F3A7",
    "HEAR_NO_EVIL_MONKEY": "0x1F649",
    "HEART_DECORATION": "0x1F49F",
    "HEART_WITH_ARROW": "0x1F498",
    "HEART_WITH_RIBBON": "0x1F49D",
    "HEAVY_BLACK_HEART": "0x2764",
    "HEAVY_CHECK_MARK": "0x2714",
    "HEAVY_DIVISION_SIGN": "0x2797",
    "HEAVY_DOLLAR_SIGN": "0x1F4B2",
    "HEAVY_EXCLAMATION_MARK_SYMBOL": "0x2757",
    "HEAVY_HEART_EXCLAMATION_MARK_ORNAMENT": "0x2763",
    "HEAVY_LARGE_CIRCLE": "0x2B55",
    "HEAVY_MINUS_SIGN": "0x2796",
    "HEAVY_MULTIPLICATION_X": "0x2716",
    "HEAVY_PLUS_SIGN": "0x2795",
    "HEDGEHOG": "0x1F994",
    "HELICOPTER": "0x1F681",
    "HELMET_WITH_WHITE_CROSS": "0x26D1",
    "HERB": "0x1F33F",
    "HIBISCUS": "0x1F33A",
    "HIGH_HEELED_SHOE": "0x1F460",
    "HIGH_SPEED_TRAIN": "0x1F684",
    "HIGH_SPEED_TRAIN_WITH_BULLET_NOSE": "0x1F685",
    "HIGH_BRIGHTNESS_SYMBOL": "0x1F506",
    "HIGH_VOLTAGE_SIGN": "0x26A1",
    "HIKING_BOOT": "0x1F97E",
    "HINDU_TEMPLE": "0x1F6D5",
    "HIPPOPOTAMUS": "0x1F99B",
    "HOCHO": "0x1F52A",
    "HOLE": "0x1F573",
    "HONEYBEE": "0x1F41D",
    "HONEY_POT": "0x1F36F",
    "HORIZONTAL_TRAFFIC_LIGHT": "0x1F6A5",
    "HORSE": "0x1F40E",
    "HORSE_FACE": "0x1F434",
    "HORSE_RACING": "0x1F3C7",
    "HOSPITAL": "0x1F3E5",
    "HOTEL": "0x1F3E8",
    "HOT_BEVERAGE": "0x2615",
    "HOT_DOG": "0x1F32D",
    "HOT_PEPPER": "0x1F336",
    "HOT_SPRINGS": "0x2668",
    "HOURGLASS": "0x231B",
    "HOURGLASS_WITH_FLOWING_SAND": "0x23F3",
    "HOUSE_BUILDING": "0x1F3E0",
    "HOUSE_BUILDINGS": "0x1F3D8",
    "HOUSE_WITH_GARDEN": "0x1F3E1",
    "HUGGING_FACE": "0x1F917",
    "HUNDRED_POINTS_SYMBOL": "0x1F4AF",
    "HUSHED_FACE": "0x1F62F",
    "ICE_CREAM": "0x1F368",
    "ICE_CUBE": "0x1F9CA",
    "ICE_HOCKEY_STICK_AND_PUCK": "0x1F3D2",
    "ICE_SKATE": "0x26F8",
    "IMP": "0x1F47F",
    "INBOX_TRAY": "0x1F4E5",
    "INCOMING_ENVELOPE": "0x1F4E8",
    "INFINITY": "0x267E",
    "INFORMATION_DESK_PERSON": "0x1F481",
    "INFORMATION_SOURCE": "0x2139",
    "INPUT_SYMBOL_FOR_LATIN_CAPITAL_LETTERS": "0x1F520",
    "INPUT_SYMBOL_FOR_LATIN_LETTERS": "0x1F524",
    "INPUT_SYMBOL_FOR_LATIN_SMALL_LETTERS": "0x1F521",
    "INPUT_SYMBOL_FOR_NUMBERS": "0x1F522",
    "INPUT_SYMBOL_FOR_SYMBOLS": "0x1F523",
    "IZAKAYA_LANTERN": "0x1F3EE",
    "JACK_O_LANTERN": "0x1F383",
    "JAPANESE_CASTLE": "0x1F3EF",
    "JAPANESE_DOLLS": "0x1F38E",
    "JAPANESE_GOBLIN": "0x1F47A",
    "JAPANESE_OGRE": "0x1F479",
    "JAPANESE_POST_OFFICE": "0x1F3E3",
    "JAPANESE_SYMBOL_FOR_BEGINNER": "0x1F530",
    "JEANS": "0x1F456",
    "JIGSAW_PUZZLE_PIECE": "0x1F9E9",
    "JOYSTICK": "0x1F579",
    "JUGGLING": "0x1F939",
    "KAABA": "0x1F54B",
    "KANGAROO": "0x1F998",
    "KEY": "0x1F511",
    "KEYBOARD": "0x2328",
    "KEYCAP_TEN": "0x1F51F",
    "KIMONO": "0x1F458",
    "KISS": "0x1F48F",
    "KISSING_CAT_FACE_WITH_CLOSED_EYES": "0x1F63D",
    "KISSING_FACE": "0x1F617",
    "KISSING_FACE_WITH_CLOSED_EYES": "0x1F61A",
    "KISSING_FACE_WITH_SMILING_EYES": "0x1F619",
    "KISS_MARK": "0x1F48B",
    "KITE": "0x1FA81",
    "KIWIFRUIT": "0x1F95D",
    "KNEELING_PERSON": "0x1F9CE",
    "KOALA": "0x1F428",
    "LABEL": "0x1F3F7",
    "LAB_COAT": "0x1F97C",
    "LADY_BEETLE": "0x1F41E",
    "LARGE_BLUE_CIRCLE": "0x1F535",
    "LARGE_BLUE_DIAMOND": "0x1F537",
    "LARGE_BLUE_SQUARE": "0x1F7E6",
    "LARGE_BROWN_CIRCLE": "0x1F7E4",
    "LARGE_BROWN_SQUARE": "0x1F7EB",
    "LARGE_GREEN_CIRCLE": "0x1F7E2",
    "LARGE_GREEN_SQUARE": "0x1F7E9",
    "LARGE_ORANGE_CIRCLE": "0x1F7E0",
    "LARGE_ORANGE_DIAMOND": "0x1F536",
    "LARGE_ORANGE_SQUARE": "0x1F7E7",
    "LARGE_PURPLE_CIRCLE": "0x1F7E3",
    "LARGE_PURPLE_SQUARE": "0x1F7EA",
    "LARGE_RED_CIRCLE": "0x1F534",
    "LARGE_RED_SQUARE": "0x1F7E5",
    "LARGE_YELLOW_CIRCLE": "0x1F7E1",
    "LARGE_YELLOW_SQUARE": "0x1F7E8",
    "LAST_QUARTER_MOON_SYMBOL": "0x1F317",
    "LAST_QUARTER_MOON_WITH_FACE": "0x1F31C",
    "LATIN_CROSS": "0x271D",
    "LEAFY_GREEN": "0x1F96C",
    "LEAF_FLUTTERING_IN_WIND": "0x1F343",
    "LEDGER": "0x1F4D2",
    "LEFT_FACING_FIST": "0x1F91B",
    "LEFT_POINTING_MAGNIFYING_GLASS": "0x1F50D",
    "LEFTWARDS_ARROW_WITH_HOOK": "0x21A9",
    "LEFTWARDS_BLACK_ARROW": "0x2B05",
    "LEFT_LUGGAGE": "0x1F6C5",
    "LEFT_RIGHT_ARROW": "0x2194",
    "LEFT_SPEECH_BUBBLE": "0x1F5E8",
    "LEG": "0x1F9B5",
    "LEMON": "0x1F34B",
    "LEO": "0x264C",
    "LEOPARD": "0x1F406",
    "LEVEL_SLIDER": "0x1F39A",
    "LIBRA": "0x264E",
    "LIGHT_RAIL": "0x1F688",
    "LINKED_PAPERCLIPS": "0x1F587",
    "LINK_SYMBOL": "0x1F517",
    "LION_FACE": "0x1F981",
    "LIPSTICK": "0x1F484",
    "LIZARD": "0x1F98E",
    "LLAMA": "0x1F999",
    "LOBSTER": "0x1F99E",
    "LOCK": "0x1F512",
    "LOCK_WITH_INK_PEN": "0x1F50F",
    "LOLLIPOP": "0x1F36D",
    "LOTION_BOTTLE": "0x1F9F4",
    "LOUDLY_CRYING_FACE": "0x1F62D",
    "LOVE_HOTEL": "0x1F3E9",
    "LOVE_LETTER": "0x1F48C",
    "LOWER_LEFT_BALLPOINT_PEN": "0x1F58A",
    "LOWER_LEFT_CRAYON": "0x1F58D",
    "LOWER_LEFT_FOUNTAIN_PEN": "0x1F58B",
    "LOWER_LEFT_PAINTBRUSH": "0x1F58C",
    "LOW_BRIGHTNESS_SYMBOL": "0x1F505",
    "LUGGAGE": "0x1F9F3",
    "LYING_FACE": "0x1F925",
    "MAGE": "0x1F9D9",
    "MAGNET": "0x1F9F2",
    "MAHJONG_TILE_RED_DRAGON": "0x1F004",
    "MALE_SIGN": "0x2642",
    "MAN": "0x1F468",
    "MANGO": "0x1F96D",
    "MANS_SHOE": "0x1F45E",
    "MANTELPIECE_CLOCK": "0x1F570",
    "MANUAL_WHEELCHAIR": "0x1F9BD",
    "MAN_AND_WOMAN_HOLDING_HANDS": "0x1F46B",
    "MAN_DANCING": "0x1F57A",
    "MAN_IN_BUSINESS_SUIT_LEVITATING": "0x1F574",
    "MAN_IN_TUXEDO": "0x1F935",
    "MAN_WITH_GUA_PI_MAO": "0x1F472",
    "MAN_WITH_TURBAN": "0x1F473",
    "MAPLE_LEAF": "0x1F341",
    "MARTIAL_ARTS_UNIFORM": "0x1F94B",
    "MATE_DRINK": "0x1F9C9",
    "MEAT_ON_BONE": "0x1F356",
    "MECHANICAL_ARM": "0x1F9BE",
    "MECHANICAL_LEG": "0x1F9BF",
    "MEDIUM_BLACK_CIRCLE": "0x26AB",
    "MEDIUM_WHITE_CIRCLE": "0x26AA",
    "MELON": "0x1F348",
    "MEMO": "0x1F4DD",
    "MENORAH_WITH_NINE_BRANCHES": "0x1F54E",
    "MENS_SYMBOL": "0x1F6B9",
    "MERPERSON": "0x1F9DC",
    "METRO": "0x1F687",
    "MICROBE": "0x1F9A0",
    "MICROPHONE": "0x1F3A4",
    "MICROSCOPE": "0x1F52C",
    "MILITARY_MEDAL": "0x1F396",
    "MILKY_WAY": "0x1F30C",
    "MINIBUS": "0x1F690",
    "MINIDISC": "0x1F4BD",
    "MOBILE_PHONE": "0x1F4F1",
    "MOBILE_PHONE_OFF": "0x1F4F4",
    "MOBILE_PHONE_WITH_RIGHTWARDS_ARROW_AT_LEFT": "0x1F4F2",
    "MONEY_MOUTH_FACE": "0x1F911",
    "MONEY_BAG": "0x1F4B0",
    "MONEY_WITH_WINGS": "0x1F4B8",
    "MONKEY": "0x1F412",
    "MONKEY_FACE": "0x1F435",
    "MONORAIL": "0x1F69D",
    "MOON_CAKE": "0x1F96E",
    "MOON_VIEWING_CEREMONY": "0x1F391",
    "MOSQUE": "0x1F54C",
    "MOSQUITO": "0x1F99F",
    "MOTHER_CHRISTMAS": "0x1F936",
    "MOTORIZED_WHEELCHAIR": "0x1F9BC",
    "MOTORWAY": "0x1F6E3",
    "MOTOR_BOAT": "0x1F6E5",
    "MOTOR_SCOOTER": "0x1F6F5",
    "MOUNTAIN": "0x26F0",
    "MOUNTAIN_BICYCLIST": "0x1F6B5",
    "MOUNTAIN_CABLEWAY": "0x1F6A0",
    "MOUNTAIN_RAILWAY": "0x1F69E",
    "MOUNT_FUJI": "0x1F5FB",
    "MOUSE": "0x1F401",
    "MOUSE_FACE": "0x1F42D",
    "MOUTH": "0x1F444",
    "MOVIE_CAMERA": "0x1F3A5",
    "MOYAI": "0x1F5FF",
    "MULTIPLE_MUSICAL_NOTES": "0x1F3B6",
    "MUSHROOM": "0x1F344",
    "MUSICAL_KEYBOARD": "0x1F3B9",
    "MUSICAL_NOTE": "0x1F3B5",
    "MUSICAL_SCORE": "0x1F3BC",
    "NAIL_POLISH": "0x1F485",
    "NAME_BADGE": "0x1F4DB",
    "NATIONAL_PARK": "0x1F3DE",
    "NAUSEATED_FACE": "0x1F922",
    "NECKTIE": "0x1F454",
    "NEGATIVE_SQUARED_AB": "0x1F18E",
    "NEGATIVE_SQUARED_CROSS_MARK": "0x274E",
    "NEGATIVE_SQUARED_LATIN_CAPITAL_LETTER_A": "0x1F170",
    "NEGATIVE_SQUARED_LATIN_CAPITAL_LETTER_B": "0x1F171",
    "NEGATIVE_SQUARED_LATIN_CAPITAL_LETTER_O": "0x1F17E",
    "NEGATIVE_SQUARED_LATIN_CAPITAL_LETTER_P": "0x1F17F",
    "NERD_FACE": "0x1F913",
    "NEUTRAL_FACE": "0x1F610",
    "NEWSPAPER": "0x1F4F0",
    "NEW_MOON_SYMBOL": "0x1F311",
    "NEW_MOON_WITH_FACE": "0x1F31A",
    "NIGHT_WITH_STARS": "0x1F303",
    "NON_POTABLE_WATER_SYMBOL": "0x1F6B1",
    "NORTH_EAST_ARROW": "0x2197",
    "NORTH_WEST_ARROW": "0x2196",
    "NOSE": "0x1F443",
    "NOTEBOOK": "0x1F4D3",
    "NOTEBOOK_WITH_DECORATIVE_COVER": "0x1F4D4",
    "NO_BICYCLES": "0x1F6B3",
    "NO_ENTRY": "0x26D4",
    "NO_ENTRY_SIGN": "0x1F6AB",
    "NO_MOBILE_PHONES": "0x1F4F5",
    "NO_ONE_UNDER_EIGHTEEN_SYMBOL": "0x1F51E",
    "NO_PEDESTRIANS": "0x1F6B7",
    "NO_SMOKING_SYMBOL": "0x1F6AD",
    "NUMBER_SIGN": "0x0023",
    "NUT_AND_BOLT": "0x1F529",
    "OCTAGONAL_SIGN": "0x1F6D1",
    "OCTOPUS": "0x1F419",
    "ODEN": "0x1F362",
    "OFFICE_BUILDING": "0x1F3E2",
    "OIL_DRUM": "0x1F6E2",
    "OK_HAND_SIGN": "0x1F44C",
    "OLDER_ADULT": "0x1F9D3",
    "OLDER_MAN": "0x1F474",
    "OLDER_WOMAN": "0x1F475",
    "OLD_KEY": "0x1F5DD",
    "OM_SYMBOL": "0x1F549",
    "ONCOMING_AUTOMOBILE": "0x1F698",
    "ONCOMING_BUS": "0x1F68D",
    "ONCOMING_POLICE_CAR": "0x1F694",
    "ONCOMING_TAXI": "0x1F696",
    "ONE_PIECE_SWIMSUIT": "0x1FA71",
    "ONION": "0x1F9C5",
    "ON_WITH_EXCLAMATION_MARK_WITH_LEFT_RIGHT_ARROW_ABOVE": "0x1F51B",
    "OPEN_BOOK": "0x1F4D6",
    "OPEN_FILE_FOLDER": "0x1F4C2",
    "OPEN_HANDS_SIGN": "0x1F450",
    "OPEN_LOCK": "0x1F513",
    "OPEN_MAILBOX_WITH_LOWERED_FLAG": "0x1F4ED",
    "OPEN_MAILBOX_WITH_RAISED_FLAG": "0x1F4EC",
    "OPHIUCHUS": "0x26CE",
    "OPTICAL_DISC": "0x1F4BF",
    "ORANGE_BOOK": "0x1F4D9",
    "ORANGE_HEART": "0x1F9E1",
    "ORANGUTAN": "0x1F9A7",
    "ORTHODOX_CROSS": "0x2626",
    "OTTER": "0x1F9A6",
    "OUTBOX_TRAY": "0x1F4E4",
    "OVERHEATED_FACE": "0x1F975",
    "OWL": "0x1F989",
    "OX": "0x1F402",
    "OYSTER": "0x1F9AA",
    "PACKAGE": "0x1F4E6",
    "PAGER": "0x1F4DF",
    "PAGE_FACING_UP": "0x1F4C4",
    "PAGE_WITH_CURL": "0x1F4C3",
    "PALM_TREE": "0x1F334",
    "PANCAKES": "0x1F95E",
    "PANDA_FACE": "0x1F43C",
    "PAPERCLIP": "0x1F4CE",
    "PARACHUTE": "0x1FA82",
    "PARROT": "0x1F99C",
    "PARTY_POPPER": "0x1F389",
    "PART_ALTERNATION_MARK": "0x303D",
    "PASSENGER_SHIP": "0x1F6F3",
    "PASSPORT_CONTROL": "0x1F6C2",
    "PAW_PRINTS": "0x1F43E",
    "PEACE_SYMBOL": "0x262E",
    "PEACH": "0x1F351",
    "PEACOCK": "0x1F99A",
    "PEANUTS": "0x1F95C",
    "PEAR": "0x1F350",
    "PEDESTRIAN": "0x1F6B6",
    "PENCIL": "0x270F",
    "PENGUIN": "0x1F427",
    "PENSIVE_FACE": "0x1F614",
    "PERFORMING_ARTS": "0x1F3AD",
    "PERSEVERING_FACE": "0x1F623",
    "PERSONAL_COMPUTER": "0x1F4BB",
    "PERSON_BOWING_DEEPLY": "0x1F647",
    "PERSON_CLIMBING": "0x1F9D7",
    "PERSON_DOING_CARTWHEEL": "0x1F938",
    "PERSON_FROWNING": "0x1F64D",
    "PERSON_IN_LOTUS_POSITION": "0x1F9D8",
    "PERSON_IN_STEAMY_ROOM": "0x1F9D6",
    "PERSON_RAISING_BOTH_HANDS_IN_CELEBRATION": "0x1F64C",
    "PERSON_WITH_BALL": "0x26F9",
    "PERSON_WITH_BLOND_HAIR": "0x1F471",
    "PERSON_WITH_FOLDED_HANDS": "0x1F64F",
    "PERSON_WITH_HEADSCARF": "0x1F9D5",
    "PERSON_WITH_POUTING_FACE": "0x1F64E",
    "PETRI_DISH": "0x1F9EB",
    "PICK": "0x26CF",
    "PIE": "0x1F967",
    "PIG": "0x1F416",
    "PIG_FACE": "0x1F437",
    "PIG_NOSE": "0x1F43D",
    "PILE_OF_POO": "0x1F4A9",
    "PILL": "0x1F48A",
    "PINCHING_HAND": "0x1F90F",
    "PINEAPPLE": "0x1F34D",
    "PINE_DECORATION": "0x1F38D",
    "PISCES": "0x2653",
    "PISTOL": "0x1F52B",
    "PLACE_OF_WORSHIP": "0x1F6D0",
    "PLAYING_CARD_BLACK_JOKER": "0x1F0CF",
    "POLICE_CAR": "0x1F693",
    "POLICE_CARS_REVOLVING_LIGHT": "0x1F6A8",
    "POLICE_OFFICER": "0x1F46E",
    "POODLE": "0x1F429",
    "POPCORN": "0x1F37F",
    "POSTAL_HORN": "0x1F4EF",
    "POSTBOX": "0x1F4EE",
    "POTABLE_WATER_SYMBOL": "0x1F6B0",
    "POTATO": "0x1F954",
    "POT_OF_FOOD": "0x1F372",
    "POUCH": "0x1F45D",
    "POULTRY_LEG": "0x1F357",
    "POUTING_CAT_FACE": "0x1F63E",
    "POUTING_FACE": "0x1F621",
    "PRAYER_BEADS": "0x1F4FF",
    "PREGNANT_WOMAN": "0x1F930",
    "PRETZEL": "0x1F968",
    "PRINCE": "0x1F934",
    "PRINCESS": "0x1F478",
    "PRINTER": "0x1F5A8",
    "PROBING_CANE": "0x1F9AF",
    "PUBLIC_ADDRESS_LOUDSPEAKER": "0x1F4E2",
    "PURPLE_HEART": "0x1F49C",
    "PURSE": "0x1F45B",
    "PUSHPIN": "0x1F4CC",
    "PUT_LITTER_IN_ITS_PLACE_SYMBOL": "0x1F6AE",
    "RABBIT": "0x1F407",
    "RABBIT_FACE": "0x1F430",
    "RACCOON": "0x1F99D",
    "RACING_CAR": "0x1F3CE",
    "RACING_MOTORCYCLE": "0x1F3CD",
    "RADIO": "0x1F4FB",
    "RADIOACTIVE_SIGN": "0x2622",
    "RADIO_BUTTON": "0x1F518",
    "RAILWAY_CAR": "0x1F683",
    "RAILWAY_TRACK": "0x1F6E4",
    "RAINBOW": "0x1F308",
    "RAISED_BACK_OF_HAND": "0x1F91A",
    "RAISED_FIST": "0x270A",
    "RAISED_HAND": "0x270B",
    "RAISED_HAND_WITH_FINGERS_SPLAYED": "0x1F590",
    "RAISED_HAND_WITH_PART_BETWEEN_MIDDLE_AND_RING_FINGERS": "0x1F596",
    "RAM": "0x1F40F",
    "RAT": "0x1F400",
    "RAZOR": "0x1FA92",
    "RECEIPT": "0x1F9FE",
    "RECREATIONAL_VEHICLE": "0x1F699",
    "RED_APPLE": "0x1F34E",
    "RED_GIFT_ENVELOPE": "0x1F9E7",
    "REGIONAL_INDICATOR_SYMBOL_LETTER_A": "0x1F1E6",
    "REGIONAL_INDICATOR_SYMBOL_LETTER_B": "0x1F1E7",
    "REGIONAL_INDICATOR_SYMBOL_LETTER_C": "0x1F1E8",
    "REGIONAL_INDICATOR_SYMBOL_LETTER_D": "0x1F1E9",
    "REGIONAL_INDICATOR_SYMBOL_LETTER_E": "0x1F1EA",
    "REGIONAL_INDICATOR_SYMBOL_LETTER_F": "0x1F1EB",
    "REGIONAL_INDICATOR_SYMBOL_LETTER_G": "0x1F1EC",
    "REGIONAL_INDICATOR_SYMBOL_LETTER_H": "0x1F1ED",
    "REGIONAL_INDICATOR_SYMBOL_LETTER_I": "0x1F1EE",
    "REGIONAL_INDICATOR_SYMBOL_LETTER_J": "0x1F1EF",
    "REGIONAL_INDICATOR_SYMBOL_LETTER_K": "0x1F1F0",
    "REGIONAL_INDICATOR_SYMBOL_LETTER_L": "0x1F1F1",
    "REGIONAL_INDICATOR_SYMBOL_LETTER_M": "0x1F1F2",
    "REGIONAL_INDICATOR_SYMBOL_LETTER_N": "0x1F1F3",
    "REGIONAL_INDICATOR_SYMBOL_LETTER_O": "0x1F1F4",
    "REGIONAL_INDICATOR_SYMBOL_LETTER_P": "0x1F1F5",
    "REGIONAL_INDICATOR_SYMBOL_LETTER_Q": "0x1F1F6",
    "REGIONAL_INDICATOR_SYMBOL_LETTER_R": "0x1F1F7",
    "REGIONAL_INDICATOR_SYMBOL_LETTER_S": "0x1F1F8",
    "REGIONAL_INDICATOR_SYMBOL_LETTER_T": "0x1F1F9",
    "REGIONAL_INDICATOR_SYMBOL_LETTER_U": "0x1F1FA",
    "REGIONAL_INDICATOR_SYMBOL_LETTER_V": "0x1F1FB",
    "REGIONAL_INDICATOR_SYMBOL_LETTER_W": "0x1F1FC",
    "REGIONAL_INDICATOR_SYMBOL_LETTER_X": "0x1F1FD",
    "REGIONAL_INDICATOR_SYMBOL_LETTER_Y": "0x1F1FE",
    "REGIONAL_INDICATOR_SYMBOL_LETTER_Z": "0x1F1FF",
    "REGISTERED_SIGN": "0x00AE",
    "RELIEVED_FACE": "0x1F60C",
    "REMINDER_RIBBON": "0x1F397",
    "RESTROOM": "0x1F6BB",
    "REVERSED_HAND_WITH_MIDDLE_FINGER_EXTENDED": "0x1F595",
    "REVOLVING_HEARTS": "0x1F49E",
    "RHINOCEROS": "0x1F98F",
    "RIBBON": "0x1F380",
    "RICE_BALL": "0x1F359",
    "RICE_CRACKER": "0x1F358",
    "RIGHT_FACING_FIST": "0x1F91C",
    "RIGHT_POINTING_MAGNIFYING_GLASS": "0x1F50E",
    "RIGHTWARDS_ARROW_WITH_HOOK": "0x21AA",
    "RIGHT_ANGER_BUBBLE": "0x1F5EF",
    "RING": "0x1F48D",
    "RINGED_PLANET": "0x1FA90",
    "ROASTED_SWEET_POTATO": "0x1F360",
    "ROBOT_FACE": "0x1F916",
    "ROCKET": "0x1F680",
    "ROLLED_UP_NEWSPAPER": "0x1F5DE",
    "ROLLER_COASTER": "0x1F3A2",
    "ROLLING_ON_THE_FLOOR_LAUGHING": "0x1F923",
    "ROLL_OF_PAPER": "0x1F9FB",
    "ROOSTER": "0x1F413",
    "ROSE": "0x1F339",
    "ROSETTE": "0x1F3F5",
    "ROUND_PUSHPIN": "0x1F4CD",
    "ROWBOAT": "0x1F6A3",
    "RUGBY_FOOTBALL": "0x1F3C9",
    "RUNNER": "0x1F3C3",
    "RUNNING_SHIRT_WITH_SASH": "0x1F3BD",
    "SAFETY_PIN": "0x1F9F7",
    "SAFETY_VEST": "0x1F9BA",
    "SAGITTARIUS": "0x2650",
    "SAILBOAT": "0x26F5",
    "SAKE_BOTTLE_AND_CUP": "0x1F376",
    "SALT_SHAKER": "0x1F9C2",
    "SANDWICH": "0x1F96A",
    "SARI": "0x1F97B",
    "SATELLITE": "0x1F6F0",
    "SATELLITE_ANTENNA": "0x1F4E1",
    "SAUROPOD": "0x1F995",
    "SAXOPHONE": "0x1F3B7",
    "SCALES": "0x2696",
    "SCARF": "0x1F9E3",
    "SCHOOL": "0x1F3EB",
    "SCHOOL_SATCHEL": "0x1F392",
    "SCOOTER": "0x1F6F4",
    "SCORPION": "0x1F982",
    "SCORPIUS": "0x264F",
    "SCROLL": "0x1F4DC",
    "SEAT": "0x1F4BA",
    "SECOND_PLACE_MEDAL": "0x1F948",
    "SEE_NO_EVIL_MONKEY": "0x1F648",
    "SEEDLING": "0x1F331",
    "SELFIE": "0x1F933",
    "SHALLOW_PAN_OF_FOOD": "0x1F958",
    "SHAMROCK": "0x2618",
    "SHARK": "0x1F988",
    "SHAVED_ICE": "0x1F367",
    "SHEEP": "0x1F411",
    "SHIELD": "0x1F6E1",
    "SHINTO_SHRINE": "0x26E9",
    "SHIP": "0x1F6A2",
    "SHOOTING_STAR": "0x1F320",
    "SHOPPING_BAGS": "0x1F6CD",
    "SHOPPING_TROLLEY": "0x1F6D2",
    "SHORTCAKE": "0x1F370",
    "SHORTS": "0x1FA73",
    "SHOWER": "0x1F6BF",
    "SHRIMP": "0x1F990",
    "SHRUG": "0x1F937",
    "SIGN_OF_THE_HORNS": "0x1F918",
    "SILHOUETTE_OF_JAPAN": "0x1F5FE",
    "SIX_POINTED_STAR_WITH_MIDDLE_DOT": "0x1F52F",
    "SKATEBOARD": "0x1F6F9",
    "SKIER": "0x26F7",
    "SKI_AND_SKI_BOOT": "0x1F3BF",
    "SKULL": "0x1F480",
    "SKULL_AND_CROSSBONES": "0x2620",
    "SKUNK": "0x1F9A8",
    "SLED": "0x1F6F7",
    "SLEEPING_ACCOMMODATION": "0x1F6CC",
    "SLEEPING_FACE": "0x1F634",
    "SLEEPING_SYMBOL": "0x1F4A4",
    "SLEEPY_FACE": "0x1F62A",
    "SLEUTH_OR_SPY": "0x1F575",
    "SLICE_OF_PIZZA": "0x1F355",
    "SLIGHTLY_FROWNING_FACE": "0x1F641",
    "SLIGHTLY_SMILING_FACE": "0x1F642",
    "SLOTH": "0x1F9A5",
    "SLOT_MACHINE": "0x1F3B0",
    "SMALL_AIRPLANE": "0x1F6E9",
    "SMALL_BLUE_DIAMOND": "0x1F539",
    "SMALL_ORANGE_DIAMOND": "0x1F538",
    "SMILING_CAT_FACE_WITH_HEART_SHAPED_EYES": "0x1F63B",
    "SMILING_CAT_FACE_WITH_OPEN_MOUTH": "0x1F63A",
    "SMILING_FACE_WITH_HALO": "0x1F607",
    "SMILING_FACE_WITH_HEART_SHAPED_EYES": "0x1F60D",
    "SMILING_FACE_WITH_HORNS": "0x1F608",
    "SMILING_FACE_WITH_OPEN_MOUTH": "0x1F603",
    "SMILING_FACE_WITH_OPEN_MOUTH_AND_COLD_SWEAT": "0x1F605",
    "SMILING_FACE_WITH_OPEN_MOUTH_AND_SMILING_EYES": "0x1F604",
    "SMILING_FACE_WITH_OPEN_MOUTH_AND_TIGHTLY_CLOSED_EYES": "0x1F606",
    "SMILING_FACE_WITH_SMILING_EYES": "0x1F60A",
    "SMILING_FACE_WITH_SMILING_EYES_AND_THREE_HEARTS": "0x1F970",
    "SMILING_FACE_WITH_SUNGLASSES": "0x1F60E",
    "SMIRKING_FACE": "0x1F60F",
    "SMOKING_SYMBOL": "0x1F6AC",
    "SNAIL": "0x1F40C",
    "SNAKE": "0x1F40D",
    "SNEEZING_FACE": "0x1F927",
    "SNOWBOARDER": "0x1F3C2",
    "SNOWFLAKE": "0x2744",
    "SNOWMAN": "0x2603",
    "SNOWMAN_WITHOUT_SNOW": "0x26C4",
    "SNOW_CAPPED_MOUNTAIN": "0x1F3D4",
    "SOCCER_BALL": "0x26BD",
    "SOCKS": "0x1F9E6",
    "SOFT_ICE_CREAM": "0x1F366",
    "SOON_WITH_RIGHTWARDS_ARROW_ABOVE": "0x1F51C",
    "SOUTH_EAST_ARROW": "0x2198",
    "SOUTH_WEST_ARROW": "0x2199",
    "SPAGHETTI": "0x1F35D",
    "SPARKLE": "0x2747",
    "SPARKLES": "0x2728",
    "SPARKLING_HEART": "0x1F496",
    "SPEAK_NO_EVIL_MONKEY": "0x1F64A",
    "SPEAKER": "0x1F508",
    "SPEAKER_WITH_CANCELLATION_STROKE": "0x1F507",
    "SPEAKER_WITH_ONE_SOUND_WAVE": "0x1F509",
    "SPEAKER_WITH_THREE_SOUND_WAVES": "0x1F50A",
    "SPEAKING_HEAD_IN_SILHOUETTE": "0x1F5E3",
    "SPEECH_BALLOON": "0x1F4AC",
    "SPEEDBOAT": "0x1F6A4",
    "SPIDER": "0x1F577",
    "SPIDER_WEB": "0x1F578",
    "SPIRAL_CALENDAR_PAD": "0x1F5D3",
    "SPIRAL_NOTE_PAD": "0x1F5D2",
    "SPIRAL_SHELL": "0x1F41A",
    "SPLASHING_SWEAT_SYMBOL": "0x1F4A6",
    "SPONGE": "0x1F9FD",
    "SPOOL_OF_THREAD": "0x1F9F5",
    "SPOON": "0x1F944",
    "SPORTS_MEDAL": "0x1F3C5",
    "SPOUTING_WHALE": "0x1F433",
    "SQUARED_CJK_UNIFIED_IDEOGRAPH_5272": "0x1F239",
    "SQUARED_CJK_UNIFIED_IDEOGRAPH_5408": "0x1F234",
    "SQUARED_CJK_UNIFIED_IDEOGRAPH_55B6": "0x1F23A",
    "SQUARED_CJK_UNIFIED_IDEOGRAPH_6307": "0x1F22F",
    "SQUARED_CJK_UNIFIED_IDEOGRAPH_6708": "0x1F237",
    "SQUARED_CJK_UNIFIED_IDEOGRAPH_6709": "0x1F236",
    "SQUARED_CJK_UNIFIED_IDEOGRAPH_6E80": "0x1F235",
    "SQUARED_CJK_UNIFIED_IDEOGRAPH_7121": "0x1F21A",
    "SQUARED_CJK_UNIFIED_IDEOGRAPH_7533": "0x1F238",
    "SQUARED_CJK_UNIFIED_IDEOGRAPH_7981": "0x1F232",
    "SQUARED_CJK_UNIFIED_IDEOGRAPH_7A7A": "0x1F233",
    "SQUARED_CL": "0x1F191",
    "SQUARED_COOL": "0x1F192",
    "SQUARED_FREE": "0x1F193",
    "SQUARED_ID": "0x1F194",
    "SQUARED_KATAKANA_KOKO": "0x1F201",
    "SQUARED_KATAKANA_SA": "0x1F202",
    "SQUARED_NEW": "0x1F195",
    "SQUARED_NG": "0x1F196",
    "SQUARED_OK": "0x1F197",
    "SQUARED_SOS": "0x1F198",
    "SQUARED_UP_WITH_EXCLAMATION_MARK": "0x1F199",
    "SQUARED_VS": "0x1F19A",
    "SQUID": "0x1F991",
    "STADIUM": "0x1F3DF",
    "STAFF_OF_AESCULAPIUS": "0x2695",
    "STANDING_PERSON": "0x1F9CD",
    "STAR_AND_CRESCENT": "0x262A",
    "STAR_OF_DAVID": "0x2721",
    "STATION": "0x1F689",
    "STATUE_OF_LIBERTY": "0x1F5FD",
    "STEAMING_BOWL": "0x1F35C",
    "STEAM_LOCOMOTIVE": "0x1F682",
    "STETHOSCOPE": "0x1FA7A",
    "STOPWATCH": "0x23F1",
    "STRAIGHT_RULER": "0x1F4CF",
    "STRAWBERRY": "0x1F353",
    "STUDIO_MICROPHONE": "0x1F399",
    "STUFFED_FLATBREAD": "0x1F959",
    "SUNFLOWER": "0x1F33B",
    "SUNRISE": "0x1F305",
    "SUNRISE_OVER_MOUNTAINS": "0x1F304",
    "SUNSET_OVER_BUILDINGS": "0x1F307",
    "SUN_BEHIND_CLOUD": "0x26C5",
    "SUN_WITH_FACE": "0x1F31E",
    "SUPERHERO": "0x1F9B8",
    "SUPERVILLAIN": "0x1F9B9",
    "SURFER": "0x1F3C4",
    "SUSHI": "0x1F363",
    "SUSPENSION_RAILWAY": "0x1F69F",
    "SWAN": "0x1F9A2",
    "SWIMMER": "0x1F3CA",
    "SYNAGOGUE": "0x1F54D",
    "SYRINGE": "0x1F489",
    "T_REX": "0x1F996",
    "T_SHIRT": "0x1F455",
    "TABLE_TENNIS_PADDLE_AND_BALL": "0x1F3D3",
    "TACO": "0x1F32E",
    "TAKEOUT_BOX": "0x1F961",
    "TANABATA_TREE": "0x1F38B",
    "TANGERINE": "0x1F34A",
    "TAURUS": "0x2649",
    "TAXI": "0x1F695",
    "TEACUP_WITHOUT_HANDLE": "0x1F375",
    "TEAR_OFF_CALENDAR": "0x1F4C6",
    "TEDDY_BEAR": "0x1F9F8",
    "TELEPHONE_RECEIVER": "0x1F4DE",
    "TELESCOPE": "0x1F52D",
    "TELEVISION": "0x1F4FA",
    "TENNIS_RACQUET_AND_BALL": "0x1F3BE",
    "TENT": "0x26FA",
    "TEST_TUBE": "0x1F9EA",
    "THERMOMETER": "0x1F321",
    "THINKING_FACE": "0x1F914",
    "THIRD_PLACE_MEDAL": "0x1F949",
    "THOUGHT_BALLOON": "0x1F4AD",
    "THREE_BUTTON_MOUSE": "0x1F5B1",
    "THUMBS_DOWN_SIGN": "0x1F44E",
    "THUMBS_UP_SIGN": "0x1F44D",
    "THUNDER_CLOUD_AND_RAIN": "0x26C8",
    "TICKET": "0x1F3AB",
    "TIGER": "0x1F405",
    "TIGER_FACE": "0x1F42F",
    "TIMER_CLOCK": "0x23F2",
    "TIRED_FACE": "0x1F62B",
    "TOILET": "0x1F6BD",
    "TOKYO_TOWER": "0x1F5FC",
    "TOMATO": "0x1F345",
    "TONGUE": "0x1F445",
    "TOOLBOX": "0x1F9F0",
    "TOOTH": "0x1F9B7",
    "TOP_HAT": "0x1F3A9",
    "TOP_WITH_UPWARDS_ARROW_ABOVE": "0x1F51D",
    "TRACKBALL": "0x1F5B2",
    "TRACTOR": "0x1F69C",
    "TRADE_MARK_SIGN": "0x2122",
    "TRAIN": "0x1F686",
    "TRAM": "0x1F68A",
    "TRAM_CAR": "0x1F68B",
    "TRIANGULAR_FLAG_ON_POST": "0x1F6A9",
    "TRIANGULAR_RULER": "0x1F4D0",
    "TRIDENT_EMBLEM": "0x1F531",
    "TROLLEYBUS": "0x1F68E",
    "TROPHY": "0x1F3C6",
    "TROPICAL_DRINK": "0x1F379",
    "TROPICAL_FISH": "0x1F420",
    "TRUMPET": "0x1F3BA",
    "TULIP": "0x1F337",
    "TUMBLER_GLASS": "0x1F943",
    "TURKEY": "0x1F983",
    "TURTLE": "0x1F422",
    "TWISTED_RIGHTWARDS_ARROWS": "0x1F500",
    "TWO_HEARTS": "0x1F495",
    "TWO_MEN_HOLDING_HANDS": "0x1F46C",
    "TWO_WOMEN_HOLDING_HANDS": "0x1F46D",
    "UMBRELLA": "0x2602",
    "UMBRELLA_ON_GROUND": "0x26F1",
    "UMBRELLA_WITH_RAIN_DROPS": "0x2614",
    "UNAMUSED_FACE": "0x1F612",
    "UNICORN_FACE": "0x1F984",
    "UP_POINTING_RED_TRIANGLE": "0x1F53A",
    "UP_POINTING_SMALL_RED_TRIANGLE": "0x1F53C",
    "UPSIDE_DOWN_FACE": "0x1F643",
    "UPWARDS_BLACK_ARROW": "0x2B06",
    "UP_DOWN_ARROW": "0x2195",
    "VAMPIRE": "0x1F9DB",
    "VERTICAL_TRAFFIC_LIGHT": "0x1F6A6",
    "VIBRATION_MODE": "0x1F4F3",
    "VICTORY_HAND": "0x270C",
    "VIDEOCASSETTE": "0x1F4FC",
    "VIDEO_CAMERA": "0x1F4F9",
    "VIDEO_GAME": "0x1F3AE",
    "VIOLIN": "0x1F3BB",
    "VIRGO": "0x264D",
    "VOLCANO": "0x1F30B",
    "VOLLEYBALL": "0x1F3D0",
    "WAFFLE": "0x1F9C7",
    "WANING_CRESCENT_MOON_SYMBOL": "0x1F318",
    "WANING_GIBBOUS_MOON_SYMBOL": "0x1F316",
    "WARNING_SIGN": "0x26A0",
    "WASTEBASKET": "0x1F5D1",
    "WATCH": "0x231A",
    "WATERMELON": "0x1F349",
    "WATER_BUFFALO": "0x1F403",
    "WATER_CLOSET": "0x1F6BE",
    "WATER_POLO": "0x1F93D",
    "WATER_WAVE": "0x1F30A",
    "WAVING_BLACK_FLAG": "0x1F3F4",
    "WAVING_HAND_SIGN": "0x1F44B",
    "WAVING_WHITE_FLAG": "0x1F3F3",
    "WAVY_DASH": "0x3030",
    "WAXING_CRESCENT_MOON_SYMBOL": "0x1F312",
    "WAXING_GIBBOUS_MOON_SYMBOL": "0x1F314",
    "WEARY_CAT_FACE": "0x1F640",
    "WEARY_FACE": "0x1F629",
    "WEDDING": "0x1F492",
    "WEIGHT_LIFTER": "0x1F3CB",
    "WHALE": "0x1F40B",
    "WHEELCHAIR_SYMBOL": "0x267F",
    "WHEEL_OF_DHARMA": "0x2638",
    "WHITE_DOWN_POINTING_BACKHAND_INDEX": "0x1F447",
    "WHITE_EXCLAMATION_MARK_ORNAMENT": "0x2755",
    "WHITE_FLOWER": "0x1F4AE",
    "WHITE_FROWNING_FACE": "0x2639",
    "WHITE_HEART": "0x1F90D",
    "WHITE_HEAVY_CHECK_MARK": "0x2705",
    "WHITE_LARGE_SQUARE": "0x2B1C",
    "WHITE_LEFT_POINTING_BACKHAND_INDEX": "0x1F448",
    "WHITE_MEDIUM_SMALL_SQUARE": "0x25FD",
    "WHITE_MEDIUM_SQUARE": "0x25FB",
    "WHITE_MEDIUM_STAR": "0x2B50",
    "WHITE_QUESTION_MARK_ORNAMENT": "0x2754",
    "WHITE_RIGHT_POINTING_BACKHAND_INDEX": "0x1F449",
    "WHITE_SMALL_SQUARE": "0x25AB",
    "WHITE_SMILING_FACE": "0x263A",
    "WHITE_SQUARE_BUTTON": "0x1F533",
    "WHITE_SUN_BEHIND_CLOUD": "0x1F325",
    "WHITE_SUN_BEHIND_CLOUD_WITH_RAIN": "0x1F326",
    "WHITE_SUN_WITH_SMALL_CLOUD": "0x1F324",
    "WHITE_UP_POINTING_BACKHAND_INDEX": "0x1F446",
    "WHITE_UP_POINTING_INDEX": "0x261D",
    "WILTED_FLOWER": "0x1F940",
    "WIND_BLOWING_FACE": "0x1F32C",
    "WIND_CHIME": "0x1F390",
    "WINE_GLASS": "0x1F377",
    "WINKING_FACE": "0x1F609",
    "WOLF_FACE": "0x1F43A",
    "WOMAN": "0x1F469",
    "WOMANS_BOOTS": "0x1F462",
    "WOMANS_CLOTHES": "0x1F45A",
    "WOMANS_HAT": "0x1F452",
    "WOMANS_SANDAL": "0x1F461",
    "WOMAN_WITH_BUNNY_EARS": "0x1F46F",
    "WOMENS_SYMBOL": "0x1F6BA",
    "WORLD_MAP": "0x1F5FA",
    "WORRIED_FACE": "0x1F61F",
    "WRAPPED_PRESENT": "0x1F381",
    "WRENCH": "0x1F527",
    "WRESTLERS": "0x1F93C",
    "WRITING_HAND": "0x270D",
    "YAWNING_FACE": "0x1F971",
    "YELLOW_HEART": "0x1F49B",
    "YIN_YANG": "0x262F",
    "YO_YO": "0x1FA80",
    "ZEBRA_FACE": "0x1F993",
    "ZIPPER_MOUTH_FACE": "0x1F910",
    "ZOMBIE": "0x1F9DF"
}
